README.md
setup.cfg
setup.py
weblogger/__init__.py
weblogger/outputs.py
weblogger/server.py
weblogger.egg-info/PKG-INFO
weblogger.egg-info/SOURCES.txt
weblogger.egg-info/dependency_links.txt
weblogger.egg-info/entry_points.txt
weblogger.egg-info/requires.txt
weblogger.egg-info/top_level.txt