Metadata-Version: 1.1
Name: weblogger
Version: 1.0.0
Summary: A service for logging messages sent over HTTP to various backends
Home-page: http://github.com/ivotkv/weblogger
Author: Ivo Tzvetkov
Author-email: ivotkv@gmail.com
License: MIT
Download-URL: https://github.com/ivotkv/weblogger/tarball/v1.0.0
Keywords: web,logger,logging,log
Platform: UNKNOWN
Classifier: Development Status :: 5 - Production/Stable
Classifier: License :: OSI Approved :: MIT License
Classifier: Operating System :: OS Independent
Classifier: Programming Language :: Python :: 2.7
Classifier: Programming Language :: Python :: 3.3
Classifier: Programming Language :: Python :: 3.4
Classifier: Programming Language :: Python :: 3.5
Classifier: Programming Language :: Python :: 3.6
